compliant_dynamodb/__init__.py
compliant_dynamodb/py.typed
compliant_dynamodb/_jsii/__init__.py
compliant_dynamodb/_jsii/compliantdynamodb@0.0.24.jsii.tgz
compliantdynamodb-0.0.24.dist-info/LICENSE
compliantdynamodb-0.0.24.dist-info/METADATA
compliantdynamodb-0.0.24.dist-info/WHEEL
compliantdynamodb-0.0.24.dist-info/top_level.txt
compliantdynamodb-0.0.24.dist-info/RECORD
