Metadata-Version: 2.1
Name: compliantdynamodb
Version: 0.0.24
Summary: compliantdynamodb
Home-page: https://github.com/jhornung/compliantDynamodb.git
Author: Janek<jhornung@oev.de>
License: Apache-2.0
Project-URL: Source, https://github.com/jhornung/compliantDynamodb.git
Platform: UNKNOWN
Classifier: Intended Audience :: Developers
Classifier: Operating System :: OS Independent
Classifier: Programming Language :: JavaScript
Classifier: Programming Language :: Python :: 3 :: Only
Classifier: Programming Language :: Python :: 3.6
Classifier: Programming Language :: Python :: 3.7
Classifier: Programming Language :: Python :: 3.8
Classifier: Programming Language :: Python :: 3.9
Classifier: Typing :: Typed
Classifier: Development Status :: 5 - Production/Stable
Classifier: License :: OSI Approved
Requires-Python: >=3.6
License-File: LICENSE
Requires-Dist: aws-cdk.aws-backup (<2.0.0,>=1.129.0)
Requires-Dist: aws-cdk.aws-dynamodb (<2.0.0,>=1.129.0)
Requires-Dist: aws-cdk.aws-events (<2.0.0,>=1.129.0)
Requires-Dist: aws-cdk.aws-iam (<2.0.0,>=1.129.0)
Requires-Dist: aws-cdk.aws-kinesis (<2.0.0,>=1.129.0)
Requires-Dist: aws-cdk.aws-kms (<2.0.0,>=1.129.0)
Requires-Dist: aws-cdk.core (<2.0.0,>=1.129.0)
Requires-Dist: constructs (<4.0.0,>=3.2.27)
Requires-Dist: jsii (<2.0.0,>=1.40.0)
Requires-Dist: publication (>=0.0.3)
